teardrop/__init__.py
teardrop/_about.py
teardrop/data_tools.py
teardrop/linear_models.py
teardrop/neural_models.py
teardrop/optimizers.py
teardrop/preprocessing.py
TearDrop-0.0.0.dist-info/LICENSE
TearDrop-0.0.0.dist-info/METADATA
TearDrop-0.0.0.dist-info/WHEEL
TearDrop-0.0.0.dist-info/top_level.txt
TearDrop-0.0.0.dist-info/RECORD
